Workbook

Sheet Price Calculator
A1: 3D Print Price Calculator
A2: One row per item. Fill in the yellow cells: name, version, grams and print hours are needed; the lighter yellow cells are optional - leave them blank to use the defaults on the Settings tab.
A3: Rows 5-8 are examples - type over them with your own items. Get grams and print time from Bambu Studio after slicing (for multicolor, use the total including flushed filament).
A4: Item | B4: Version | C4: Filament (g) | D4: Print time (hrs) | E4: Cleanup (min) | F4: Painting (hrs) | G4: Paint supplies ($) | H4: Hardware / extras ($) | I4: Packaging ($) | J4: Markup override | K4: Material ($) | L4: Machine time ($) | M4: Failure buffer ($) | N4: Labor ($) | O4: Supplies & packaging ($) | P4: Total cost ($) | Q4: Markup used | R4: Target price before fees ($) | S4: LIST PRICE ($) | T4: Selling fees ($) | U4: Your profit ($) | V4: Profit per print hour ($) | W4: Notes
A5: Example - Oni mask, single color | B5: Single color | C5: 200 | D5: 8 | E5: 30 | H5: 1.5 | K5: =IF(COUNT($C5:$D5)<2,"",$C5*Settings!$B$7) -> 4 | L5: =IF(COUNT($C5:$D5)<2,"",$D5*Settings!$B$8) -> 4 | M5: =IF(COUNT($C5:$D5)<2,"",($K5+$L5)*Settings!$B$9) -> 0.8 | N5: =IF(COUNT($C5:$D5)<2,"",(IF($E5="",Settings!$B$11,$E5)/60+N($F5))*Settings!$B$10) -> 10 | O5: =IF(COUNT($C5:$D5)<2,"",IF($G5="",IF($B5="Painted",Settings!$B$12,0),$G5)+N($H5)+IF($I5="",Settings!$B$13,$I5)) -> 3.5 | P5: =IF(COUNT($C5:$D5)<2,"",SUM($K5:$O5)) -> 22.3 | Q5: =IF(COUNT($C5:$D5)<2,"",IF($J5<>"",$J5,IF($B5="",Settings!$B$20,IFERROR(INDEX(Settings!$B$20:$B$22,MATCH($B5,Settings!$A$20:$A$22,0)),"")))) -> 2 | R5: =IF(OR($P5="",$Q5=""),"",$P5*$Q5) -> 44.6 | S5: =IF($R5="","",IF(Settings!$B$16>0,CEILING(($R5+Settings!$B$15)/(1-Settings!$B$14),Settings!$B$16),($R5+Settings!$B$15)/(1-Settings!$B$14))) -> 50 | T5: =IF($S5="","",$S5*Settings!$B$14+Settings!$B$15) -> 5.2 | U5: =IF($S5="","",$S5-$T5-$P5) -> 22.5 | V5: =IF(OR($U5="",N($D5)<=0),"",$U5/$D5) -> 2.8125 | W5: Strap $1.50; packaging uses the default
A6: Example - Oni mask, hand-painted | B6: Painted | C6: 230 | D6: 15 | E6: 30 | F6: 3 | H6: 1.5 | K6: =IF(COUNT($C6:$D6)<2,"",$C6*Settings!$B$7) -> 4.6 | L6: =IF(COUNT($C6:$D6)<2,"",$D6*Settings!$B$8) -> 7.5 | M6: =IF(COUNT($C6:$D6)<2,"",($K6+$L6)*Settings!$B$9) -> 1.21 | N6: =IF(COUNT($C6:$D6)<2,"",(IF($E6="",Settings!$B$11,$E6)/60+N($F6))*Settings!$B$10) -> 70 | O6: =IF(COUNT($C6:$D6)<2,"",IF($G6="",IF($B6="Painted",Settings!$B$12,0),$G6)+N($H6)+IF($I6="",Settings!$B$13,$I6)) -> 8.5 | P6: =IF(COUNT($C6:$D6)<2,"",SUM($K6:$O6)) -> 91.81 | Q6: =IF(COUNT($C6:$D6)<2,"",IF($J6<>"",$J6,IF($B6="",Settings!$B$20,IFERROR(INDEX(Settings!$B$20:$B$22,MATCH($B6,Settings!$A$20:$A$22,0)),"")))) -> 1.5 | R6: =IF(OR($P6="",$Q6=""),"",$P6*$Q6) -> 137.715 | S6: =IF($R6="","",IF(Settings!$B$16>0,CEILING(($R6+Settings!$B$15)/(1-Settings!$B$14),Settings!$B$16),($R6+Settings!$B$15)/(1-Settings!$B$14))) -> 153 | T6: =IF($S6="","",$S6*Settings!$B$14+Settings!$B$15) -> 14.985 | U6: =IF($S6="","",$S6-$T6-$P6) -> 46.205 | V6: =IF(OR($U6="",N($D6)<=0),"",$U6/$D6) -> 3.0803333 | W6: Paint supplies use the default
A7: Example - Keychain | B7: Single color | C7: 8 | D7: 0.5 | E7: 5 | H7: 0.3 | I7: 0.5 | J7: 3 | K7: =IF(COUNT($C7:$D7)<2,"",$C7*Settings!$B$7) -> 0.16 | L7: =IF(COUNT($C7:$D7)<2,"",$D7*Settings!$B$8) -> 0.25 | M7: =IF(COUNT($C7:$D7)<2,"",($K7+$L7)*Settings!$B$9) -> 0.041 | N7: =IF(COUNT($C7:$D7)<2,"",(IF($E7="",Settings!$B$11,$E7)/60+N($F7))*Settings!$B$10) -> 1.6666667 | O7: =IF(COUNT($C7:$D7)<2,"",IF($G7="",IF($B7="Painted",Settings!$B$12,0),$G7)+N($H7)+IF($I7="",Settings!$B$13,$I7)) -> 0.8 | P7: =IF(COUNT($C7:$D7)<2,"",SUM($K7:$O7)) -> 2.9176667 | Q7: =IF(COUNT($C7:$D7)<2,"",IF($J7<>"",$J7,IF($B7="",Settings!$B$20,IFERROR(INDEX(Settings!$B$20:$B$22,MATCH($B7,Settings!$A$20:$A$22,0)),"")))) -> 3 | R7: =IF(OR($P7="",$Q7=""),"",$P7*$Q7) -> 8.753 | S7: =IF($R7="","",IF(Settings!$B$16>0,CEILING(($R7+Settings!$B$15)/(1-Settings!$B$14),Settings!$B$16),($R7+Settings!$B$15)/(1-Settings!$B$14))) -> 11 | T7: =IF($S7="","",$S7*Settings!$B$14+Settings!$B$15) -> 1.495 | U7: =IF($S7="","",$S7-$T7-$P7) -> 6.5873333 | V7: =IF(OR($U7="",N($D7)<=0),"",$U7/$D7) -> 13.174667 | W7: Key ring $0.30; higher markup for a small item
A8: Example - Desk organizer | B8: Single color | C8: 245 | D8: 9 | E8: 20 | I8: 3 | K8: =IF(COUNT($C8:$D8)<2,"",$C8*Settings!$B$7) -> 4.9 | L8: =IF(COUNT($C8:$D8)<2,"",$D8*Settings!$B$8) -> 4.5 | M8: =IF(COUNT($C8:$D8)<2,"",($K8+$L8)*Settings!$B$9) -> 0.94 | N8: =IF(COUNT($C8:$D8)<2,"",(IF($E8="",Settings!$B$11,$E8)/60+N($F8))*Settings!$B$10) -> 6.6666667 | O8: =IF(COUNT($C8:$D8)<2,"",IF($G8="",IF($B8="Painted",Settings!$B$12,0),$G8)+N($H8)+IF($I8="",Settings!$B$13,$I8)) -> 3 | P8: =IF(COUNT($C8:$D8)<2,"",SUM($K8:$O8)) -> 20.006667 | Q8: =IF(COUNT($C8:$D8)<2,"",IF($J8<>"",$J8,IF($B8="",Settings!$B$20,IFERROR(INDEX(Settings!$B$20:$B$22,MATCH($B8,Settings!$A$20:$A$22,0)),"")))) -> 2 | R8: =IF(OR($P8="",$Q8=""),"",$P8*$Q8) -> 40.013333 | S8: =IF($R8="","",IF(Settings!$B$16>0,CEILING(($R8+Settings!$B$15)/(1-Settings!$B$14),Settings!$B$16),($R8+Settings!$B$15)/(1-Settings!$B$14))) -> 45 | T8: =IF($S8="","",$S8*Settings!$B$14+Settings!$B$15) -> 4.725 | U8: =IF($S8="","",$S8-$T8-$P8) -> 20.268333 | V8: =IF(OR($U8="",N($D8)<=0),"",$U8/$D8) -> 2.252037 | W8: Bigger box for shipping
K9: =IF(COUNT($C9:$D9)<2,"",$C9*Settings!$B$7) | L9: =IF(COUNT($C9:$D9)<2,"",$D9*Settings!$B$8) | M9: =IF(COUNT($C9:$D9)<2,"",($K9+$L9)*Settings!$B$9) | N9: =IF(COUNT($C9:$D9)<2,"",(IF($E9="",Settings!$B$11,$E9)/60+N($F9))*Settings!$B$10) | O9: =IF(COUNT($C9:$D9)<2,"",IF($G9="",IF($B9="Painted",Settings!$B$12,0),$G9)+N($H9)+IF($I9="",Settings!$B$13,$I9)) | P9: =IF(COUNT($C9:$D9)<2,"",SUM($K9:$O9)) | Q9: =IF(COUNT($C9:$D9)<2,"",IF($J9<>"",$J9,IF($B9="",Settings!$B$20,IFERROR(INDEX(Settings!$B$20:$B$22,MATCH($B9,Settings!$A$20:$A$22,0)),"")))) | R9: =IF(OR($P9="",$Q9=""),"",$P9*$Q9) | S9: =IF($R9="","",IF(Settings!$B$16>0,CEILING(($R9+Settings!$B$15)/(1-Settings!$B$14),Settings!$B$16),($R9+Settings!$B$15)/(1-Settings!$B$14))) | T9: =IF($S9="","",$S9*Settings!$B$14+Settings!$B$15) | U9: =IF($S9="","",$S9-$T9-$P9) | V9: =IF(OR($U9="",N($D9)<=0),"",$U9/$D9)
K10: =IF(COUNT($C10:$D10)<2,"",$C10*Settings!$B$7) | L10: =IF(COUNT($C10:$D10)<2,"",$D10*Settings!$B$8) | M10: =IF(COUNT($C10:$D10)<2,"",($K10+$L10)*Settings!$B$9) | N10: =IF(COUNT($C10:$D10)<2,"",(IF($E10="",Settings!$B$11,$E10)/60+N($F10))*Settings!$B$10) | O10: =IF(COUNT($C10:$D10)<2,"",IF($G10="",IF($B10="Painted",Settings!$B$12,0),$G10)+N($H10)+IF($I10="",Settings!$B$13,$I10)) | P10: =IF(COUNT($C10:$D10)<2,"",SUM($K10:$O10)) | Q10: =IF(COUNT($C10:$D10)<2,"",IF($J10<>"",$J10,IF($B10="",Settings!$B$20,IFERROR(INDEX(Settings!$B$20:$B$22,MATCH($B10,Settings!$A$20:$A$22,0)),"")))) | R10: =IF(OR($P10="",$Q10=""),"",$P10*$Q10) | S10: =IF($R10="","",IF(Settings!$B$16>0,CEILING(($R10+Settings!$B$15)/(1-Settings!$B$14),Settings!$B$16),($R10+Settings!$B$15)/(1-Settings!$B$14))) | T10: =IF($S10="","",$S10*Settings!$B$14+Settings!$B$15) | U10: =IF($S10="","",$S10-$T10-$P10) | V10: =IF(OR($U10="",N($D10)<=0),"",$U10/$D10)
K11: =IF(COUNT($C11:$D11)<2,"",$C11*Settings!$B$7) | L11: =IF(COUNT($C11:$D11)<2,"",$D11*Settings!$B$8) | M11: =IF(COUNT($C11:$D11)<2,"",($K11+$L11)*Settings!$B$9) | N11: =IF(COUNT($C11:$D11)<2,"",(IF($E11="",Settings!$B$11,$E11)/60+N($F11))*Settings!$B$10) | O11: =IF(COUNT($C11:$D11)<2,"",IF($G11="",IF($B11="Painted",Settings!$B$12,0),$G11)+N($H11)+IF($I11="",Settings!$B$13,$I11)) | P11: =IF(COUNT($C11:$D11)<2,"",SUM($K11:$O11)) | Q11: =IF(COUNT($C11:$D11)<2,"",IF($J11<>"",$J11,IF($B11="",Settings!$B$20,IFERROR(INDEX(Settings!$B$20:$B$22,MATCH($B11,Settings!$A$20:$A$22,0)),"")))) | R11: =IF(OR($P11="",$Q11=""),"",$P11*$Q11) | S11: =IF($R11="","",IF(Settings!$B$16>0,CEILING(($R11+Settings!$B$15)/(1-Settings!$B$14),Settings!$B$16),($R11+Settings!$B$15)/(1-Settings!$B$14))) | T11: =IF($S11="","",$S11*Settings!$B$14+Settings!$B$15) | U11: =IF($S11="","",$S11-$T11-$P11) | V11: =IF(OR($U11="",N($D11)<=0),"",$U11/$D11)
K12: =IF(COUNT($C12:$D12)<2,"",$C12*Settings!$B$7) | L12: =IF(COUNT($C12:$D12)<2,"",$D12*Settings!$B$8) | M12: =IF(COUNT($C12:$D12)<2,"",($K12+$L12)*Settings!$B$9) | N12: =IF(COUNT($C12:$D12)<2,"",(IF($E12="",Settings!$B$11,$E12)/60+N($F12))*Settings!$B$10) | O12: =IF(COUNT($C12:$D12)<2,"",IF($G12="",IF($B12="Painted",Settings!$B$12,0),$G12)+N($H12)+IF($I12="",Settings!$B$13,$I12)) | P12: =IF(COUNT($C12:$D12)<2,"",SUM($K12:$O12)) | Q12: =IF(COUNT($C12:$D12)<2,"",IF($J12<>"",$J12,IF($B12="",Settings!$B$20,IFERROR(INDEX(Settings!$B$20:$B$22,MATCH($B12,Settings!$A$20:$A$22,0)),"")))) | R12: =IF(OR($P12="",$Q12=""),"",$P12*$Q12) | S12: =IF($R12="","",IF(Settings!$B$16>0,CEILING(($R12+Settings!$B$15)/(1-Settings!$B$14),Settings!$B$16),($R12+Settings!$B$15)/(1-Settings!$B$14))) | T12: =IF($S12="","",$S12*Settings!$B$14+Settings!$B$15) | U12: =IF($S12="","",$S12-$T12-$P12) | V12: =IF(OR($U12="",N($D12)<=0),"",$U12/$D12)
K13: =IF(COUNT($C13:$D13)<2,"",$C13*Settings!$B$7) | L13: =IF(COUNT($C13:$D13)<2,"",$D13*Settings!$B$8) | M13: =IF(COUNT($C13:$D13)<2,"",($K13+$L13)*Settings!$B$9) | N13: =IF(COUNT($C13:$D13)<2,"",(IF($E13="",Settings!$B$11,$E13)/60+N($F13))*Settings!$B$10) | O13: =IF(COUNT($C13:$D13)<2,"",IF($G13="",IF($B13="Painted",Settings!$B$12,0),$G13)+N($H13)+IF($I13="",Settings!$B$13,$I13)) | P13: =IF(COUNT($C13:$D13)<2,"",SUM($K13:$O13)) | Q13: =IF(COUNT($C13:$D13)<2,"",IF($J13<>"",$J13,IF($B13="",Settings!$B$20,IFERROR(INDEX(Settings!$B$20:$B$22,MATCH($B13,Settings!$A$20:$A$22,0)),"")))) | R13: =IF(OR($P13="",$Q13=""),"",$P13*$Q13) | S13: =IF($R13="","",IF(Settings!$B$16>0,CEILING(($R13+Settings!$B$15)/(1-Settings!$B$14),Settings!$B$16),($R13+Settings!$B$15)/(1-Settings!$B$14))) | T13: =IF($S13="","",$S13*Settings!$B$14+Settings!$B$15) | U13: =IF($S13="","",$S13-$T13-$P13) | V13: =IF(OR($U13="",N($D13)<=0),"",$U13/$D13)
K14: =IF(COUNT($C14:$D14)<2,"",$C14*Settings!$B$7) | L14: =IF(COUNT($C14:$D14)<2,"",$D14*Settings!$B$8) | M14: =IF(COUNT($C14:$D14)<2,"",($K14+$L14)*Settings!$B$9) | N14: =IF(COUNT($C14:$D14)<2,"",(IF($E14="",Settings!$B$11,$E14)/60+N($F14))*Settings!$B$10) | O14: =IF(COUNT($C14:$D14)<2,"",IF($G14="",IF($B14="Painted",Settings!$B$12,0),$G14)+N($H14)+IF($I14="",Settings!$B$13,$I14)) | P14: =IF(COUNT($C14:$D14)<2,"",SUM($K14:$O14)) | Q14: =IF(COUNT($C14:$D14)<2,"",IF($J14<>"",$J14,IF($B14="",Settings!$B$20,IFERROR(INDEX(Settings!$B$20:$B$22,MATCH($B14,Settings!$A$20:$A$22,0)),"")))) | R14: =IF(OR($P14="",$Q14=""),"",$P14*$Q14) | S14: =IF($R14="","",IF(Settings!$B$16>0,CEILING(($R14+Settings!$B$15)/(1-Settings!$B$14),Settings!$B$16),($R14+Settings!$B$15)/(1-Settings!$B$14))) | T14: =IF($S14="","",$S14*Settings!$B$14+Settings!$B$15) | U14: =IF($S14="","",$S14-$T14-$P14) | V14: =IF(OR($U14="",N($D14)<=0),"",$U14/$D14)
K15: =IF(COUNT($C15:$D15)<2,"",$C15*Settings!$B$7) | L15: =IF(COUNT($C15:$D15)<2,"",$D15*Settings!$B$8) | M15: =IF(COUNT($C15:$D15)<2,"",($K15+$L15)*Settings!$B$9) | N15: =IF(COUNT($C15:$D15)<2,"",(IF($E15="",Settings!$B$11,$E15)/60+N($F15))*Settings!$B$10) | O15: =IF(COUNT($C15:$D15)<2,"",IF($G15="",IF($B15="Painted",Settings!$B$12,0),$G15)+N($H15)+IF($I15="",Settings!$B$13,$I15)) | P15: =IF(COUNT($C15:$D15)<2,"",SUM($K15:$O15)) | Q15: =IF(COUNT($C15:$D15)<2,"",IF($J15<>"",$J15,IF($B15="",Settings!$B$20,IFERROR(INDEX(Settings!$B$20:$B$22,MATCH($B15,Settings!$A$20:$A$22,0)),"")))) | R15: =IF(OR($P15="",$Q15=""),"",$P15*$Q15) | S15: =IF($R15="","",IF(Settings!$B$16>0,CEILING(($R15+Settings!$B$15)/(1-Settings!$B$14),Settings!$B$16),($R15+Settings!$B$15)/(1-Settings!$B$14))) | T15: =IF($S15="","",$S15*Settings!$B$14+Settings!$B$15) | U15: =IF($S15="","",$S15-$T15-$P15) | V15: =IF(OR($U15="",N($D15)<=0),"",$U15/$D15)
K16: =IF(COUNT($C16:$D16)<2,"",$C16*Settings!$B$7) | L16: =IF(COUNT($C16:$D16)<2,"",$D16*Settings!$B$8) | M16: =IF(COUNT($C16:$D16)<2,"",($K16+$L16)*Settings!$B$9) | N16: =IF(COUNT($C16:$D16)<2,"",(IF($E16="",Settings!$B$11,$E16)/60+N($F16))*Settings!$B$10) | O16: =IF(COUNT($C16:$D16)<2,"",IF($G16="",IF($B16="Painted",Settings!$B$12,0),$G16)+N($H16)+IF($I16="",Settings!$B$13,$I16)) | P16: =IF(COUNT($C16:$D16)<2,"",SUM($K16:$O16)) | Q16: =IF(COUNT($C16:$D16)<2,"",IF($J16<>"",$J16,IF($B16="",Settings!$B$20,IFERROR(INDEX(Settings!$B$20:$B$22,MATCH($B16,Settings!$A$20:$A$22,0)),"")))) | R16: =IF(OR($P16="",$Q16=""),"",$P16*$Q16) | S16: =IF($R16="","",IF(Settings!$B$16>0,CEILING(($R16+Settings!$B$15)/(1-Settings!$B$14),Settings!$B$16),($R16+Settings!$B$15)/(1-Settings!$B$14))) | T16: =IF($S16="","",$S16*Settings!$B$14+Settings!$B$15) | U16: =IF($S16="","",$S16-$T16-$P16) | V16: =IF(OR($U16="",N($D16)<=0),"",$U16/$D16)
K17: =IF(COUNT($C17:$D17)<2,"",$C17*Settings!$B$7) | L17: =IF(COUNT($C17:$D17)<2,"",$D17*Settings!$B$8) | M17: =IF(COUNT($C17:$D17)<2,"",($K17+$L17)*Settings!$B$9) | N17: =IF(COUNT($C17:$D17)<2,"",(IF($E17="",Settings!$B$11,$E17)/60+N($F17))*Settings!$B$10) | O17: =IF(COUNT($C17:$D17)<2,"",IF($G17="",IF($B17="Painted",Settings!$B$12,0),$G17)+N($H17)+IF($I17="",Settings!$B$13,$I17)) | P17: =IF(COUNT($C17:$D17)<2,"",SUM($K17:$O17)) | Q17: =IF(COUNT($C17:$D17)<2,"",IF($J17<>"",$J17,IF($B17="",Settings!$B$20,IFERROR(INDEX(Settings!$B$20:$B$22,MATCH($B17,Settings!$A$20:$A$22,0)),"")))) | R17: =IF(OR($P17="",$Q17=""),"",$P17*$Q17) | S17: =IF($R17="","",IF(Settings!$B$16>0,CEILING(($R17+Settings!$B$15)/(1-Settings!$B$14),Settings!$B$16),($R17+Settings!$B$15)/(1-Settings!$B$14))) | T17: =IF($S17="","",$S17*Settings!$B$14+Settings!$B$15) | U17: =IF($S17="","",$S17-$T17-$P17) | V17: =IF(OR($U17="",N($D17)<=0),"",$U17/$D17)
K18: =IF(COUNT($C18:$D18)<2,"",$C18*Settings!$B$7) | L18: =IF(COUNT($C18:$D18)<2,"",$D18*Settings!$B$8) | M18: =IF(COUNT($C18:$D18)<2,"",($K18+$L18)*Settings!$B$9) | N18: =IF(COUNT($C18:$D18)<2,"",(IF($E18="",Settings!$B$11,$E18)/60+N($F18))*Settings!$B$10) | O18: =IF(COUNT($C18:$D18)<2,"",IF($G18="",IF($B18="Painted",Settings!$B$12,0),$G18)+N($H18)+IF($I18="",Settings!$B$13,$I18)) | P18: =IF(COUNT($C18:$D18)<2,"",SUM($K18:$O18)) | Q18: =IF(COUNT($C18:$D18)<2,"",IF($J18<>"",$J18,IF($B18="",Settings!$B$20,IFERROR(INDEX(Settings!$B$20:$B$22,MATCH($B18,Settings!$A$20:$A$22,0)),"")))) | R18: =IF(OR($P18="",$Q18=""),"",$P18*$Q18) | S18: =IF($R18="","",IF(Settings!$B$16>0,CEILING(($R18+Settings!$B$15)/(1-Settings!$B$14),Settings!$B$16),($R18+Settings!$B$15)/(1-Settings!$B$14))) | T18: =IF($S18="","",$S18*Settings!$B$14+Settings!$B$15) | U18: =IF($S18="","",$S18-$T18-$P18) | V18: =IF(OR($U18="",N($D18)<=0),"",$U18/$D18)
K19: =IF(COUNT($C19:$D19)<2,"",$C19*Settings!$B$7) | L19: =IF(COUNT($C19:$D19)<2,"",$D19*Settings!$B$8) | M19: =IF(COUNT($C19:$D19)<2,"",($K19+$L19)*Settings!$B$9) | N19: =IF(COUNT($C19:$D19)<2,"",(IF($E19="",Settings!$B$11,$E19)/60+N($F19))*Settings!$B$10) | O19: =IF(COUNT($C19:$D19)<2,"",IF($G19="",IF($B19="Painted",Settings!$B$12,0),$G19)+N($H19)+IF($I19="",Settings!$B$13,$I19)) | P19: =IF(COUNT($C19:$D19)<2,"",SUM($K19:$O19)) | Q19: =IF(COUNT($C19:$D19)<2,"",IF($J19<>"",$J19,IF($B19="",Settings!$B$20,IFERROR(INDEX(Settings!$B$20:$B$22,MATCH($B19,Settings!$A$20:$A$22,0)),"")))) | R19: =IF(OR($P19="",$Q19=""),"",$P19*$Q19) | S19: =IF($R19="","",IF(Settings!$B$16>0,CEILING(($R19+Settings!$B$15)/(1-Settings!$B$14),Settings!$B$16),($R19+Settings!$B$15)/(1-Settings!$B$14))) | T19: =IF($S19="","",$S19*Settings!$B$14+Settings!$B$15) | U19: =IF($S19="","",$S19-$T19-$P19) | V19: =IF(OR($U19="",N($D19)<=0),"",$U19/$D19)
K20: =IF(COUNT($C20:$D20)<2,"",$C20*Settings!$B$7) | L20: =IF(COUNT($C20:$D20)<2,"",$D20*Settings!$B$8) | M20: =IF(COUNT($C20:$D20)<2,"",($K20+$L20)*Settings!$B$9) | N20: =IF(COUNT($C20:$D20)<2,"",(IF($E20="",Settings!$B$11,$E20)/60+N($F20))*Settings!$B$10) | O20: =IF(COUNT($C20:$D20)<2,"",IF($G20="",IF($B20="Painted",Settings!$B$12,0),$G20)+N($H20)+IF($I20="",Settings!$B$13,$I20)) | P20: =IF(COUNT($C20:$D20)<2,"",SUM($K20:$O20)) | Q20: =IF(COUNT($C20:$D20)<2,"",IF($J20<>"",$J20,IF($B20="",Settings!$B$20,IFERROR(INDEX(Settings!$B$20:$B$22,MATCH($B20,Settings!$A$20:$A$22,0)),"")))) | R20: =IF(OR($P20="",$Q20=""),"",$P20*$Q20) | S20: =IF($R20="","",IF(Settings!$B$16>0,CEILING(($R20+Settings!$B$15)/(1-Settings!$B$14),Settings!$B$16),($R20+Settings!$B$15)/(1-Settings!$B$14))) | T20: =IF($S20="","",$S20*Settings!$B$14+Settings!$B$15) | U20: =IF($S20="","",$S20-$T20-$P20) | V20: =IF(OR($U20="",N($D20)<=0),"",$U20/$D20)
... K104: =IF(COUNT($C104:$D104)<2,"",$C104*Settings!$B$7) | L104: =IF(COUNT($C104:$D104)<2,"",$D104*Settings!$B$8) | M104: =IF(COUNT($C104:$D104)<2,"",($K104+$L104)*Settings!$B$9) | N104: =IF(COUNT($C104:$D104)<2,"",(IF($E104="",Settings!$B$11,$E104)/60+N($F104))*Settings!$B$10) | O104: =IF(COUNT($C104:$D104)<2,"",IF($G104="",IF($B104="Painted",Settings!$B$12,0),$G104)+N($H104)+IF($I104="",Settings!$B$13,$I104)) | P104: =IF(COUNT($C104:$D104)<2,"",SUM($K104:$O104)) | Q104: =IF(COUNT($C104:$D104)<2,"",IF($J104<>"",$J104,IF($B104="",Settings!$B$20,IFERROR(INDEX(Settings!$B$20:$B$22,MATCH($B104,Settings!$A$20:$A$22,0)),"")))) | R104: =IF(OR($P104="",$Q104=""),"",$P104*$Q104) | S104: =IF($R104="","",IF(Settings!$B$16>0,CEILING(($R104+Settings!$B$15)/(1-Settings!$B$14),Settings!$B$16),($R104+Settings!$B$15)/(1-Settings!$B$14))) | T104: =IF($S104="","",$S104*Settings!$B$14+Settings!$B$15) | U104: =IF($S104="","",$S104-$T104-$P104) | V104: =IF(OR($U104="",N($D104)<=0),"",$U104/$D104)

Sheet Settings
A1: Settings - shared costs and defaults for every item
A2: Yellow cells with blue text are yours to change. Gray cells calculate automatically. Defaults are used when an item's own cell on the Price Calculator is left blank.
A4: Setting | B4: Value | C4: What it means / where the number came from
A5: Filament spool price ($) | B5: 20 | C5: What you pay for one spool. Starting estimate - change it to your real price.
A6: Spool weight (g) | B6: 1000 | C6: Most spools are 1 kg (1000 g).
A7: Filament cost per gram ($) | B7: =IF(B6>0,B5/B6,0) -> 0.02 | C7: Calculated: spool price / spool weight.
A8: Machine rate ($ per print hour) | B8: 0.5 | C8: Covers electricity (only a few cents an hour on a P2S), nozzle and plate wear, and paying off the printer. Common rule-of-thumb estimate.
A9: Failure buffer (%) | B9: 0.1 | C9: Extra added to material + machine cost to cover prints that fail.
A10: Your labor rate ($/hr) | B10: 20 | C10: What you pay yourself for hands-on work (cleanup and painting).
A11: Default cleanup time (minutes) | B11: 15 | C11: Used when an item's Cleanup cell is blank: removing supports, sanding, assembly, packing.
A12: Default paint supplies, painted items ($) | B12: 5 | C12: Used when a 'Painted' item's Paint supplies cell is blank: primer, paint and clear coat.
A13: Default packaging ($) | B13: 2 | C13: Used when an item's Packaging cell is blank: box or mailer, padding, label.
A14: Selling fee (%) | B14: 0.095 | C14: Etsy (US, as of 2025): 6.5% transaction fee + 3% payment processing. Offsite Ads sales cost an extra 12-15%. Set to 0% for cash or in-person sales. Check current fees: https://www.etsy.com/legal/fees/
A15: Fixed fee per sale ($) | B15: 0.45 | C15: Etsy (US, as of 2025): $0.20 listing fee + $0.25 payment processing. Set to 0 for in-person sales.
A16: Round list price up to nearest ($) | B16: 1 | C16: Keeps prices tidy, e.g. $49.78 becomes $50. Use 5 to round to the next $5, or 0 for no rounding.
A18: Markup by version
A19: Version | B19: Markup | C19: Why this multiplier
A20: Single color | B20: 2 | C20: One filament, no paint. Starting point; compare with what similar items sell for.
A21: Multicolor | B21: 2.5 | C21: Printed in several colors with the AMS - looks finished without paint, so it sells at a premium.
A22: Painted | B22: 1.5 | C22: Lower multiplier because your painting hours are already paid at your labor rate.
A23: Keep the version names as they are - the calculator's dropdown uses them. Any item can override its markup in the 'Markup override' column.
A24: The markups were picked against 3D-printed Oni masks on Etsy (unpainted ~$41-65, hand-painted ~$129-175; etsy.com/market/3d_printed_oni_mask, checked Oct 2026). Small, cheap items usually need a higher markup - see the keychain example.

Sheet How to Use
A1: How to use this calculator
A3: 1. Open the Settings tab and change the yellow cells to match your real costs (spool price, your hourly rate, fees) and your usual cleanup time and packaging.
A4: 2. On the Price Calculator tab, add one row per item: name, version (dropdown), and grams and print time from Bambu Studio.
A5: 3. Fill in the lighter yellow cells only where an item is different: its own cleanup time, painting hours, paint supplies, hardware (straps, magnets, key rings), packaging, or a different markup. Blank cells use the defaults on the Settings tab; type 0 for none.
A6: 4. The green LIST PRICE column is what to list it for. It already covers Etsy's fees.
A7: 5. Compare that price with similar items on Etsy. If yours is much higher, lower the markup (per item with Markup override, or per version on the Settings tab) or find ways to cut print or hands-on time.
A8: 6. Use 'Profit per print hour' to see which items make the best use of your printer.
A10: Tips
A11: - Time yourself on your first few painted pieces and use real hours - painting is usually the biggest cost.
A12: - Small, cheap prints (keychains, magnets) usually need a markup of 3x or more, because your hands-on time and fees are a big share of the price.
A13: - Selling in person or with cash? Set the selling fee % and fixed fee to 0 on the Settings tab.
A14: - 'Your profit' is extra money after paying yourself your labor rate for cleanup and painting.
... A19: Yellow with blue text = needed input. Lighter yellow = optional input (blank uses the defaults). Green = the price to list. White/gray = calculated, don't type here.
