Workbook

Sheet Price Calculator
A1: Oni Mask Price Calculator
A2: Fill in the yellow cells for each mask (name, version, grams, print hours, painting hours). Everything else calculates. Change shared costs on the Settings tab.
A3: Rows 5-7 are examples - type over them with your own masks. Get grams and print time from Bambu Studio after slicing (for multicolor, use the total including flushed filament).
A4: Mask name | B4: Version | C4: Filament (g) | D4: Print time (hrs) | E4: Painting time (hrs) | F4: Material ($) | G4: Machine time ($) | H4: Failure buffer ($) | I4: Cleanup labor ($) | J4: Painting ($) | K4: Strap & packaging ($) | L4: Total cost ($) | M4: Markup | N4: Target price before fees ($) | O4: LIST PRICE ($) | P4: Selling fees ($) | Q4: Your profit ($) | R4: Profit per print hour ($) | S4: Notes
A5: Example - Oni (8 hr print) | B5: Unpainted | C5: 200 | D5: 8 | F5: =IF(COUNT($C5:$D5)<2,"",$C5*Settings!$B$7) -> 4 | G5: =IF(COUNT($C5:$D5)<2,"",$D5*Settings!$B$8) -> 4 | H5: =IF(COUNT($C5:$D5)<2,"",($F5+$G5)*Settings!$B$9) -> 0.8 | I5: =IF(COUNT($C5:$D5)<2,"",Settings!$B$11/60*Settings!$B$10) -> 10 | J5: =IF(COUNT($C5:$D5)<2,"",N($E5)*Settings!$B$10+IF($B5="Painted",Settings!$B$12,0)) -> 0 | K5: =IF(COUNT($C5:$D5)<2,"",Settings!$B$13+Settings!$B$14) -> 3.5 | L5: =IF(COUNT($C5:$D5)<2,"",SUM($F5:$K5)) -> 22.3 | M5: =IF(OR(COUNT($C5:$D5)<2,$B5=""),"",IFERROR(INDEX(Settings!$B$21:$B$23,MATCH($B5,Settings!$A$21:$A$23,0)),"")) -> 2 | N5: =IF(OR($L5="",$M5=""),"",$L5*$M5) -> 44.6 | O5: =IF($N5="","",IF(Settings!$B$17>0,CEILING(($N5+Settings!$B$16)/(1-Settings!$B$15),Settings!$B$17),($N5+Settings!$B$16)/(1-Settings!$B$15))) -> 50 | P5: =IF($O5="","",$O5*Settings!$B$15+Settings!$B$16) -> 5.2 | Q5: =IF($O5="","",$O5-$P5-$L5) -> 22.5 | R5: =IF(OR($Q5="",N($D5)<=0),"",$Q5/$D5) -> 2.8125 | S5: Etsy unpainted: ~$41-65
A6: Example - Oni multicolor (12 hr) | B6: Multicolor | C6: 260 | D6: 12 | F6: =IF(COUNT($C6:$D6)<2,"",$C6*Settings!$B$7) -> 5.2 | G6: =IF(COUNT($C6:$D6)<2,"",$D6*Settings!$B$8) -> 6 | H6: =IF(COUNT($C6:$D6)<2,"",($F6+$G6)*Settings!$B$9) -> 1.12 | I6: =IF(COUNT($C6:$D6)<2,"",Settings!$B$11/60*Settings!$B$10) -> 10 | J6: =IF(COUNT($C6:$D6)<2,"",N($E6)*Settings!$B$10+IF($B6="Painted",Settings!$B$12,0)) -> 0 | K6: =IF(COUNT($C6:$D6)<2,"",Settings!$B$13+Settings!$B$14) -> 3.5 | L6: =IF(COUNT($C6:$D6)<2,"",SUM($F6:$K6)) -> 25.82 | M6: =IF(OR(COUNT($C6:$D6)<2,$B6=""),"",IFERROR(INDEX(Settings!$B$21:$B$23,MATCH($B6,Settings!$A$21:$A$23,0)),"")) -> 2.5 | N6: =IF(OR($L6="",$M6=""),"",$L6*$M6) -> 64.55 | O6: =IF($N6="","",IF(Settings!$B$17>0,CEILING(($N6+Settings!$B$16)/(1-Settings!$B$15),Settings!$B$17),($N6+Settings!$B$16)/(1-Settings!$B$15))) -> 75 | P6: =IF($O6="","",$O6*Settings!$B$15+Settings!$B$16) -> 7.575 | Q6: =IF($O6="","",$O6-$P6-$L6) -> 41.605 | R6: =IF(OR($Q6="",N($D6)<=0),"",$Q6/$D6) -> 3.4670833 | S6: Grams include AMS flush
A7: Example - Oni hand-painted (15 hr) | B7: Painted | C7: 230 | D7: 15 | E7: 3 | F7: =IF(COUNT($C7:$D7)<2,"",$C7*Settings!$B$7) -> 4.6 | G7: =IF(COUNT($C7:$D7)<2,"",$D7*Settings!$B$8) -> 7.5 | H7: =IF(COUNT($C7:$D7)<2,"",($F7+$G7)*Settings!$B$9) -> 1.21 | I7: =IF(COUNT($C7:$D7)<2,"",Settings!$B$11/60*Settings!$B$10) -> 10 | J7: =IF(COUNT($C7:$D7)<2,"",N($E7)*Settings!$B$10+IF($B7="Painted",Settings!$B$12,0)) -> 65 | K7: =IF(COUNT($C7:$D7)<2,"",Settings!$B$13+Settings!$B$14) -> 3.5 | L7: =IF(COUNT($C7:$D7)<2,"",SUM($F7:$K7)) -> 91.81 | M7: =IF(OR(COUNT($C7:$D7)<2,$B7=""),"",IFERROR(INDEX(Settings!$B$21:$B$23,MATCH($B7,Settings!$A$21:$A$23,0)),"")) -> 1.5 | N7: =IF(OR($L7="",$M7=""),"",$L7*$M7) -> 137.715 | O7: =IF($N7="","",IF(Settings!$B$17>0,CEILING(($N7+Settings!$B$16)/(1-Settings!$B$15),Settings!$B$17),($N7+Settings!$B$16)/(1-Settings!$B$15))) -> 155 | P7: =IF($O7="","",$O7*Settings!$B$15+Settings!$B$16) -> 15.175 | Q7: =IF($O7="","",$O7-$P7-$L7) -> 48.015 | R7: =IF(OR($Q7="",N($D7)<=0),"",$Q7/$D7) -> 3.201 | S7: Etsy painted: ~$129-175
F8: =IF(COUNT($C8:$D8)<2,"",$C8*Settings!$B$7) | G8: =IF(COUNT($C8:$D8)<2,"",$D8*Settings!$B$8) | H8: =IF(COUNT($C8:$D8)<2,"",($F8+$G8)*Settings!$B$9) | I8: =IF(COUNT($C8:$D8)<2,"",Settings!$B$11/60*Settings!$B$10) | J8: =IF(COUNT($C8:$D8)<2,"",N($E8)*Settings!$B$10+IF($B8="Painted",Settings!$B$12,0)) | K8: =IF(COUNT($C8:$D8)<2,"",Settings!$B$13+Settings!$B$14) | L8: =IF(COUNT($C8:$D8)<2,"",SUM($F8:$K8)) | M8: =IF(OR(COUNT($C8:$D8)<2,$B8=""),"",IFERROR(INDEX(Settings!$B$21:$B$23,MATCH($B8,Settings!$A$21:$A$23,0)),"")) | N8: =IF(OR($L8="",$M8=""),"",$L8*$M8) | O8: =IF($N8="","",IF(Settings!$B$17>0,CEILING(($N8+Settings!$B$16)/(1-Settings!$B$15),Settings!$B$17),($N8+Settings!$B$16)/(1-Settings!$B$15))) | P8: =IF($O8="","",$O8*Settings!$B$15+Settings!$B$16) | Q8: =IF($O8="","",$O8-$P8-$L8) | R8: =IF(OR($Q8="",N($D8)<=0),"",$Q8/$D8)
F9: =IF(COUNT($C9:$D9)<2,"",$C9*Settings!$B$7) | G9: =IF(COUNT($C9:$D9)<2,"",$D9*Settings!$B$8) | H9: =IF(COUNT($C9:$D9)<2,"",($F9+$G9)*Settings!$B$9) | I9: =IF(COUNT($C9:$D9)<2,"",Settings!$B$11/60*Settings!$B$10) | J9: =IF(COUNT($C9:$D9)<2,"",N($E9)*Settings!$B$10+IF($B9="Painted",Settings!$B$12,0)) | K9: =IF(COUNT($C9:$D9)<2,"",Settings!$B$13+Settings!$B$14) | L9: =IF(COUNT($C9:$D9)<2,"",SUM($F9:$K9)) | M9: =IF(OR(COUNT($C9:$D9)<2,$B9=""),"",IFERROR(INDEX(Settings!$B$21:$B$23,MATCH($B9,Settings!$A$21:$A$23,0)),"")) | N9: =IF(OR($L9="",$M9=""),"",$L9*$M9) | O9: =IF($N9="","",IF(Settings!$B$17>0,CEILING(($N9+Settings!$B$16)/(1-Settings!$B$15),Settings!$B$17),($N9+Settings!$B$16)/(1-Settings!$B$15))) | P9: =IF($O9="","",$O9*Settings!$B$15+Settings!$B$16) | Q9: =IF($O9="","",$O9-$P9-$L9) | R9: =IF(OR($Q9="",N($D9)<=0),"",$Q9/$D9)
F10: =IF(COUNT($C10:$D10)<2,"",$C10*Settings!$B$7) | G10: =IF(COUNT($C10:$D10)<2,"",$D10*Settings!$B$8) | H10: =IF(COUNT($C10:$D10)<2,"",($F10+$G10)*Settings!$B$9) | I10: =IF(COUNT($C10:$D10)<2,"",Settings!$B$11/60*Settings!$B$10) | J10: =IF(COUNT($C10:$D10)<2,"",N($E10)*Settings!$B$10+IF($B10="Painted",Settings!$B$12,0)) | K10: =IF(COUNT($C10:$D10)<2,"",Settings!$B$13+Settings!$B$14) | L10: =IF(COUNT($C10:$D10)<2,"",SUM($F10:$K10)) | M10: =IF(OR(COUNT($C10:$D10)<2,$B10=""),"",IFERROR(INDEX(Settings!$B$21:$B$23,MATCH($B10,Settings!$A$21:$A$23,0)),"")) | N10: =IF(OR($L10="",$M10=""),"",$L10*$M10) | O10: =IF($N10="","",IF(Settings!$B$17>0,CEILING(($N10+Settings!$B$16)/(1-Settings!$B$15),Settings!$B$17),($N10+Settings!$B$16)/(1-Settings!$B$15))) | P10: =IF($O10="","",$O10*Settings!$B$15+Settings!$B$16) | Q10: =IF($O10="","",$O10-$P10-$L10) | R10: =IF(OR($Q10="",N($D10)<=0),"",$Q10/$D10)
F11: =IF(COUNT($C11:$D11)<2,"",$C11*Settings!$B$7) | G11: =IF(COUNT($C11:$D11)<2,"",$D11*Settings!$B$8) | H11: =IF(COUNT($C11:$D11)<2,"",($F11+$G11)*Settings!$B$9) | I11: =IF(COUNT($C11:$D11)<2,"",Settings!$B$11/60*Settings!$B$10) | J11: =IF(COUNT($C11:$D11)<2,"",N($E11)*Settings!$B$10+IF($B11="Painted",Settings!$B$12,0)) | K11: =IF(COUNT($C11:$D11)<2,"",Settings!$B$13+Settings!$B$14) | L11: =IF(COUNT($C11:$D11)<2,"",SUM($F11:$K11)) | M11: =IF(OR(COUNT($C11:$D11)<2,$B11=""),"",IFERROR(INDEX(Settings!$B$21:$B$23,MATCH($B11,Settings!$A$21:$A$23,0)),"")) | N11: =IF(OR($L11="",$M11=""),"",$L11*$M11) | O11: =IF($N11="","",IF(Settings!$B$17>0,CEILING(($N11+Settings!$B$16)/(1-Settings!$B$15),Settings!$B$17),($N11+Settings!$B$16)/(1-Settings!$B$15))) | P11: =IF($O11="","",$O11*Settings!$B$15+Settings!$B$16) | Q11: =IF($O11="","",$O11-$P11-$L11) | R11: =IF(OR($Q11="",N($D11)<=0),"",$Q11/$D11)
F12: =IF(COUNT($C12:$D12)<2,"",$C12*Settings!$B$7) | G12: =IF(COUNT($C12:$D12)<2,"",$D12*Settings!$B$8) | H12: =IF(COUNT($C12:$D12)<2,"",($F12+$G12)*Settings!$B$9) | I12: =IF(COUNT($C12:$D12)<2,"",Settings!$B$11/60*Settings!$B$10) | J12: =IF(COUNT($C12:$D12)<2,"",N($E12)*Settings!$B$10+IF($B12="Painted",Settings!$B$12,0)) | K12: =IF(COUNT($C12:$D12)<2,"",Settings!$B$13+Settings!$B$14) | L12: =IF(COUNT($C12:$D12)<2,"",SUM($F12:$K12)) | M12: =IF(OR(COUNT($C12:$D12)<2,$B12=""),"",IFERROR(INDEX(Settings!$B$21:$B$23,MATCH($B12,Settings!$A$21:$A$23,0)),"")) | N12: =IF(OR($L12="",$M12=""),"",$L12*$M12) | O12: =IF($N12="","",IF(Settings!$B$17>0,CEILING(($N12+Settings!$B$16)/(1-Settings!$B$15),Settings!$B$17),($N12+Settings!$B$16)/(1-Settings!$B$15))) | P12: =IF($O12="","",$O12*Settings!$B$15+Settings!$B$16) | Q12: =IF($O12="","",$O12-$P12-$L12) | R12: =IF(OR($Q12="",N($D12)<=0),"",$Q12/$D12)
F13: =IF(COUNT($C13:$D13)<2,"",$C13*Settings!$B$7) | G13: =IF(COUNT($C13:$D13)<2,"",$D13*Settings!$B$8) | H13: =IF(COUNT($C13:$D13)<2,"",($F13+$G13)*Settings!$B$9) | I13: =IF(COUNT($C13:$D13)<2,"",Settings!$B$11/60*Settings!$B$10) | J13: =IF(COUNT($C13:$D13)<2,"",N($E13)*Settings!$B$10+IF($B13="Painted",Settings!$B$12,0)) | K13: =IF(COUNT($C13:$D13)<2,"",Settings!$B$13+Settings!$B$14) | L13: =IF(COUNT($C13:$D13)<2,"",SUM($F13:$K13)) | M13: =IF(OR(COUNT($C13:$D13)<2,$B13=""),"",IFERROR(INDEX(Settings!$B$21:$B$23,MATCH($B13,Settings!$A$21:$A$23,0)),"")) | N13: =IF(OR($L13="",$M13=""),"",$L13*$M13) | O13: =IF($N13="","",IF(Settings!$B$17>0,CEILING(($N13+Settings!$B$16)/(1-Settings!$B$15),Settings!$B$17),($N13+Settings!$B$16)/(1-Settings!$B$15))) | P13: =IF($O13="","",$O13*Settings!$B$15+Settings!$B$16) | Q13: =IF($O13="","",$O13-$P13-$L13) | R13: =IF(OR($Q13="",N($D13)<=0),"",$Q13/$D13)
F14: =IF(COUNT($C14:$D14)<2,"",$C14*Settings!$B$7) | G14: =IF(COUNT($C14:$D14)<2,"",$D14*Settings!$B$8) | H14: =IF(COUNT($C14:$D14)<2,"",($F14+$G14)*Settings!$B$9) | I14: =IF(COUNT($C14:$D14)<2,"",Settings!$B$11/60*Settings!$B$10) | J14: =IF(COUNT($C14:$D14)<2,"",N($E14)*Settings!$B$10+IF($B14="Painted",Settings!$B$12,0)) | K14: =IF(COUNT($C14:$D14)<2,"",Settings!$B$13+Settings!$B$14) | L14: =IF(COUNT($C14:$D14)<2,"",SUM($F14:$K14)) | M14: =IF(OR(COUNT($C14:$D14)<2,$B14=""),"",IFERROR(INDEX(Settings!$B$21:$B$23,MATCH($B14,Settings!$A$21:$A$23,0)),"")) | N14: =IF(OR($L14="",$M14=""),"",$L14*$M14) | O14: =IF($N14="","",IF(Settings!$B$17>0,CEILING(($N14+Settings!$B$16)/(1-Settings!$B$15),Settings!$B$17),($N14+Settings!$B$16)/(1-Settings!$B$15))) | P14: =IF($O14="","",$O14*Settings!$B$15+Settings!$B$16) | Q14: =IF($O14="","",$O14-$P14-$L14) | R14: =IF(OR($Q14="",N($D14)<=0),"",$Q14/$D14)
F15: =IF(COUNT($C15:$D15)<2,"",$C15*Settings!$B$7) | G15: =IF(COUNT($C15:$D15)<2,"",$D15*Settings!$B$8) | H15: =IF(COUNT($C15:$D15)<2,"",($F15+$G15)*Settings!$B$9) | I15: =IF(COUNT($C15:$D15)<2,"",Settings!$B$11/60*Settings!$B$10) | J15: =IF(COUNT($C15:$D15)<2,"",N($E15)*Settings!$B$10+IF($B15="Painted",Settings!$B$12,0)) | K15: =IF(COUNT($C15:$D15)<2,"",Settings!$B$13+Settings!$B$14) | L15: =IF(COUNT($C15:$D15)<2,"",SUM($F15:$K15)) | M15: =IF(OR(COUNT($C15:$D15)<2,$B15=""),"",IFERROR(INDEX(Settings!$B$21:$B$23,MATCH($B15,Settings!$A$21:$A$23,0)),"")) | N15: =IF(OR($L15="",$M15=""),"",$L15*$M15) | O15: =IF($N15="","",IF(Settings!$B$17>0,CEILING(($N15+Settings!$B$16)/(1-Settings!$B$15),Settings!$B$17),($N15+Settings!$B$16)/(1-Settings!$B$15))) | P15: =IF($O15="","",$O15*Settings!$B$15+Settings!$B$16) | Q15: =IF($O15="","",$O15-$P15-$L15) | R15: =IF(OR($Q15="",N($D15)<=0),"",$Q15/$D15)
F16: =IF(COUNT($C16:$D16)<2,"",$C16*Settings!$B$7) | G16: =IF(COUNT($C16:$D16)<2,"",$D16*Settings!$B$8) | H16: =IF(COUNT($C16:$D16)<2,"",($F16+$G16)*Settings!$B$9) | I16: =IF(COUNT($C16:$D16)<2,"",Settings!$B$11/60*Settings!$B$10) | J16: =IF(COUNT($C16:$D16)<2,"",N($E16)*Settings!$B$10+IF($B16="Painted",Settings!$B$12,0)) | K16: =IF(COUNT($C16:$D16)<2,"",Settings!$B$13+Settings!$B$14) | L16: =IF(COUNT($C16:$D16)<2,"",SUM($F16:$K16)) | M16: =IF(OR(COUNT($C16:$D16)<2,$B16=""),"",IFERROR(INDEX(Settings!$B$21:$B$23,MATCH($B16,Settings!$A$21:$A$23,0)),"")) | N16: =IF(OR($L16="",$M16=""),"",$L16*$M16) | O16: =IF($N16="","",IF(Settings!$B$17>0,CEILING(($N16+Settings!$B$16)/(1-Settings!$B$15),Settings!$B$17),($N16+Settings!$B$16)/(1-Settings!$B$15))) | P16: =IF($O16="","",$O16*Settings!$B$15+Settings!$B$16) | Q16: =IF($O16="","",$O16-$P16-$L16) | R16: =IF(OR($Q16="",N($D16)<=0),"",$Q16/$D16)
F17: =IF(COUNT($C17:$D17)<2,"",$C17*Settings!$B$7) | G17: =IF(COUNT($C17:$D17)<2,"",$D17*Settings!$B$8) | H17: =IF(COUNT($C17:$D17)<2,"",($F17+$G17)*Settings!$B$9) | I17: =IF(COUNT($C17:$D17)<2,"",Settings!$B$11/60*Settings!$B$10) | J17: =IF(COUNT($C17:$D17)<2,"",N($E17)*Settings!$B$10+IF($B17="Painted",Settings!$B$12,0)) | K17: =IF(COUNT($C17:$D17)<2,"",Settings!$B$13+Settings!$B$14) | L17: =IF(COUNT($C17:$D17)<2,"",SUM($F17:$K17)) | M17: =IF(OR(COUNT($C17:$D17)<2,$B17=""),"",IFERROR(INDEX(Settings!$B$21:$B$23,MATCH($B17,Settings!$A$21:$A$23,0)),"")) | N17: =IF(OR($L17="",$M17=""),"",$L17*$M17) | O17: =IF($N17="","",IF(Settings!$B$17>0,CEILING(($N17+Settings!$B$16)/(1-Settings!$B$15),Settings!$B$17),($N17+Settings!$B$16)/(1-Settings!$B$15))) | P17: =IF($O17="","",$O17*Settings!$B$15+Settings!$B$16) | Q17: =IF($O17="","",$O17-$P17-$L17) | R17: =IF(OR($Q17="",N($D17)<=0),"",$Q17/$D17)
F18: =IF(COUNT($C18:$D18)<2,"",$C18*Settings!$B$7) | G18: =IF(COUNT($C18:$D18)<2,"",$D18*Settings!$B$8) | H18: =IF(COUNT($C18:$D18)<2,"",($F18+$G18)*Settings!$B$9) | I18: =IF(COUNT($C18:$D18)<2,"",Settings!$B$11/60*Settings!$B$10) | J18: =IF(COUNT($C18:$D18)<2,"",N($E18)*Settings!$B$10+IF($B18="Painted",Settings!$B$12,0)) | K18: =IF(COUNT($C18:$D18)<2,"",Settings!$B$13+Settings!$B$14) | L18: =IF(COUNT($C18:$D18)<2,"",SUM($F18:$K18)) | M18: =IF(OR(COUNT($C18:$D18)<2,$B18=""),"",IFERROR(INDEX(Settings!$B$21:$B$23,MATCH($B18,Settings!$A$21:$A$23,0)),"")) | N18: =IF(OR($L18="",$M18=""),"",$L18*$M18) | O18: =IF($N18="","",IF(Settings!$B$17>0,CEILING(($N18+Settings!$B$16)/(1-Settings!$B$15),Settings!$B$17),($N18+Settings!$B$16)/(1-Settings!$B$15))) | P18: =IF($O18="","",$O18*Settings!$B$15+Settings!$B$16) | Q18: =IF($O18="","",$O18-$P18-$L18) | R18: =IF(OR($Q18="",N($D18)<=0),"",$Q18/$D18)
F19: =IF(COUNT($C19:$D19)<2,"",$C19*Settings!$B$7) | G19: =IF(COUNT($C19:$D19)<2,"",$D19*Settings!$B$8) | H19: =IF(COUNT($C19:$D19)<2,"",($F19+$G19)*Settings!$B$9) | I19: =IF(COUNT($C19:$D19)<2,"",Settings!$B$11/60*Settings!$B$10) | J19: =IF(COUNT($C19:$D19)<2,"",N($E19)*Settings!$B$10+IF($B19="Painted",Settings!$B$12,0)) | K19: =IF(COUNT($C19:$D19)<2,"",Settings!$B$13+Settings!$B$14) | L19: =IF(COUNT($C19:$D19)<2,"",SUM($F19:$K19)) | M19: =IF(OR(COUNT($C19:$D19)<2,$B19=""),"",IFERROR(INDEX(Settings!$B$21:$B$23,MATCH($B19,Settings!$A$21:$A$23,0)),"")) | N19: =IF(OR($L19="",$M19=""),"",$L19*$M19) | O19: =IF($N19="","",IF(Settings!$B$17>0,CEILING(($N19+Settings!$B$16)/(1-Settings!$B$15),Settings!$B$17),($N19+Settings!$B$16)/(1-Settings!$B$15))) | P19: =IF($O19="","",$O19*Settings!$B$15+Settings!$B$16) | Q19: =IF($O19="","",$O19-$P19-$L19) | R19: =IF(OR($Q19="",N($D19)<=0),"",$Q19/$D19)
... F54: =IF(COUNT($C54:$D54)<2,"",$C54*Settings!$B$7) | G54: =IF(COUNT($C54:$D54)<2,"",$D54*Settings!$B$8) | H54: =IF(COUNT($C54:$D54)<2,"",($F54+$G54)*Settings!$B$9) | I54: =IF(COUNT($C54:$D54)<2,"",Settings!$B$11/60*Settings!$B$10) | J54: =IF(COUNT($C54:$D54)<2,"",N($E54)*Settings!$B$10+IF($B54="Painted",Settings!$B$12,0)) | K54: =IF(COUNT($C54:$D54)<2,"",Settings!$B$13+Settings!$B$14) | L54: =IF(COUNT($C54:$D54)<2,"",SUM($F54:$K54)) | M54: =IF(OR(COUNT($C54:$D54)<2,$B54=""),"",IFERROR(INDEX(Settings!$B$21:$B$23,MATCH($B54,Settings!$A$21:$A$23,0)),"")) | N54: =IF(OR($L54="",$M54=""),"",$L54*$M54) | O54: =IF($N54="","",IF(Settings!$B$17>0,CEILING(($N54+Settings!$B$16)/(1-Settings!$B$15),Settings!$B$17),($N54+Settings!$B$16)/(1-Settings!$B$15))) | P54: =IF($O54="","",$O54*Settings!$B$15+Settings!$B$16) | Q54: =IF($O54="","",$O54-$P54-$L54) | R54: =IF(OR($Q54="",N($D54)<=0),"",$Q54/$D54)

Sheet Settings
A1: Settings - shared costs used for every mask
A2: Yellow cells with blue text are yours to change. Gray cells calculate automatically.
A4: Setting | B4: Value | C4: What it means / where the number came from
A5: Filament spool price ($) | B5: 20 | C5: What you pay for one spool of PLA. Starting estimate - change it to your real price.
A6: Spool weight (g) | B6: 1000 | C6: Most PLA spools are 1 kg (1000 g).
A7: Filament cost per gram ($) | B7: =IF(B6>0,B5/B6,0) -> 0.02 | C7: Calculated: spool price / spool weight.
A8: Machine rate ($ per print hour) | B8: 0.5 | C8: Covers electricity (only a few cents an hour on a P2S), nozzle and plate wear, and paying off the printer. Common rule-of-thumb estimate.
A9: Failure buffer (%) | B9: 0.1 | C9: Extra added to material + machine cost to cover prints that fail.
A10: Your labor rate ($/hr) | B10: 20 | C10: What you pay yourself for hands-on work (cleanup and painting).
A11: Cleanup time per mask (minutes) | B11: 30 | C11: Removing supports, light sanding, attaching the strap, packing.
A12: Paint supplies per painted mask ($) | B12: 5 | C12: Your share of primer, acrylic paint and clear coat used on one mask. Only added to 'Painted' masks.
A13: Strap / eye mesh per mask ($) | B13: 1.5 | C13: Elastic strap, eye mesh or other wearable hardware. Set to 0 for display-only masks.
A14: Packaging per mask ($) | B14: 2 | C14: Box, tissue or bubble wrap, label.
A15: Selling fee (%) | B15: 0.095 | C15: Etsy (US, as of 2025): 6.5% transaction fee + 3% payment processing. Offsite Ads sales cost an extra 12-15%. Set to 0% for cash or in-person sales. Check current fees: https://www.etsy.com/legal/fees/
A16: Fixed fee per sale ($) | B16: 0.45 | C16: Etsy (US, as of 2025): $0.20 listing fee + $0.25 payment processing. Set to 0 for in-person sales.
A17: Round list price up to nearest ($) | B17: 5 | C17: Keeps prices tidy, e.g. $62.10 becomes $65. Use 1 for whole dollars.
A19: Markup by version
A20: Version | B20: Markup | C20: Why this multiplier
A21: Unpainted | B21: 2 | C21: Single-color print. Similar 3D-printed Oni masks on Etsy list for about $41-65.
A22: Multicolor | B22: 2.5 | C22: Printed in several colors with the AMS - looks finished without paint, so it sells at a premium.
A23: Painted | B23: 1.5 | C23: Lower multiplier because your painting hours are already paid at your labor rate. Similar hand-painted masks on Etsy list for about $129-175.
A24: Keep the version names as they are - the calculator's dropdown uses them.
A25: Etsy price ranges: etsy.com/market/3d_printed_oni_mask and etsy.com/market/oni_wearable_mask, checked Oct 2026.

Sheet How to Use
A1: How to use this calculator
A3: 1. Open the Settings tab and change the yellow cells to match your real costs (spool price, your hourly rate, packaging, fees).
A4: 2. On the Price Calculator tab, add one row per mask: name, version (dropdown), grams and print time from Bambu Studio, and painting hours if painted.
A5: 3. The green LIST PRICE column is what to list it for. It already covers Etsy's fees.
A6: 4. Compare that price with similar masks on Etsy. If yours is much higher, lower the markup on the Settings tab or find ways to cut print or painting time.
A7: 5. Use 'Profit per print hour' to see which masks make the best use of your printer.
A9: Tips
A10: - Time yourself on your first few painted masks and use real hours - painting is the biggest cost.
A11: - Selling in person or with cash? Set the selling fee % and fixed fee to 0 on the Settings tab.
A12: - 'Your profit' is extra money after paying yourself your labor rate for cleanup and painting.
A13: - Red numbers in the profit columns mean that mask loses money at the current settings.
A14: - Check the model's license allows selling prints before you list it.
... A17: Yellow with blue text = your input. Green = the price to list. White/gray = calculated, don't type here.
